highball/__init__.py
highball/api.py
highball/middleware.py
highball/response.py
highball-0.0.2.dist-info/METADATA
highball-0.0.2.dist-info/WHEEL
highball-0.0.2.dist-info/top_level.txt
highball-0.0.2.dist-info/RECORD
